LICENSE
README.rst
setup.cfg
setup.py
jpbizday/__init__.py
jpbizday/jpbizday.py
jpbizday.egg-info/PKG-INFO
jpbizday.egg-info/SOURCES.txt
jpbizday.egg-info/dependency_links.txt
jpbizday.egg-info/requires.txt
jpbizday.egg-info/top_level.txt