Metadata-Version: 1.2
Name: jpbizday
Version: 0.0.3
Summary: Pure-Python Japan Business Day Generator
Home-page: https://github.com/sig9org/jpbizday
Author: sig9
Author-email: sig9@sig9.org
Maintainer: sig9
Maintainer-email: sig9@sig9.org
License: MIT License
Keywords: Business Day,Holiday,Japan
Platform: POSIX
Platform: Windows
Platform: Unix
Platform: MacOS
Classifier: Intended Audience :: Developers
Classifier: License :: OSI Approved :: MIT License
Classifier: Natural Language :: Japanese
Classifier: Operating System :: MacOS
Classifier: Operating System :: Microsoft
Classifier: Operating System :: POSIX
Classifier: Programming Language :: Python :: 3 :: Only
Classifier: Programming Language :: Python :: 3.4
Classifier: Programming Language :: Python :: 3.5
Classifier: Programming Language :: Python :: 3.6
Classifier: Programming Language :: Python :: 3.7
Classifier: Programming Language :: Python :: 3.8
